alt_tabpy/__init__.py
alt_tabpy/__main__.py
alt_tabpy/handlers.py
tests/__init__.py
tests/test_handlers.py
alt_tabpy-0.0.2.dist-info/LICENSE
alt_tabpy-0.0.2.dist-info/METADATA
alt_tabpy-0.0.2.dist-info/WHEEL
alt_tabpy-0.0.2.dist-info/top_level.txt
alt_tabpy-0.0.2.dist-info/RECORD
