Metadata-Version: 2.1
Name: alt-tabpy
Version: 0.0.2
Summary: A lightweight TabPy implementation
Home-page: https://alttabpy.readthedocs.io/en/latest/index.html
Author: Will Ayd
Author-email: will_ayd@innobi.io
License: UNKNOWN
Platform: UNKNOWN
Classifier: Programming Language :: Python :: 3
Classifier: License :: OSI Approved :: MIT License
Classifier: Operating System :: OS Independent
Requires-Python: >=3.6
Requires-Dist: tornado
